{
    "images": [
        {
            "id": 18,
            "width": 640,
            "height": 640,
            "file_name": "34_FP_Lumino.png"
        }
    ],
    "annotations": [
        {
            "id": 187,
            "image_id": 18,
            "category_id": 16,
            "bbox": [
                133,
                249,
                109.878,
                87.308
            ],
            "area": 9593.198,
            "segmentation": [
                [
                    135.235,
                    249.111,
                    142.842,
                    276.926,
                    133.544,
                    277.488,
                    132.7,
                    336.418,
                    242.578,
                    332.555,
                    240.042,
                    249.883,
                    135.235,
                    249.111
                ]
            ],
            "iscrowd": 0
        },
        {
            "id": 188,
            "image_id": 18,
            "category_id": 15,
            "bbox": [
                139,
                83,
                164.818,
                160.707
            ],
            "area": 26487.407,
            "segmentation": [
                [
                    178.341,
                    127.035,
                    141.151,
                    125.49,
                    138.616,
                    240.386,
                    303.434,
                    243.703,
                    300.898,
                    82.995,
                    180.877,
                    82.995,
                    178.341,
                    127.035
                ]
            ],
            "iscrowd": 0
        },
        {
            "id": 189,
            "image_id": 18,
            "category_id": 13,
            "bbox": [
                238,
                79,
                222.292,
                255.646
            ],
            "area": 56828.217,
            "segmentation": [
                [
                    425.99,
                    331.01,
                    423.455,
                    288.515,
                    352.456,
                    285.425,
                    352.456,
                    225.932,
                    457.264,
                    223.614,
                    460.644,
                    82.995,
                    303.434,
                    79.227,
                    305.969,
                    243.703,
                    238.352,
                    244.475,
                    240.887,
                    334.873,
                    425.99,
                    331.01
                ]
            ],
            "iscrowd": 0
        },
        {
            "id": 190,
            "image_id": 18,
            "category_id": 22,
            "bbox": [
                139,
                81,
                32.964,
                38.631
            ],
            "area": 1273.429,
            "segmentation": [
                [
                    138.616,
                    82.705,
                    141.997,
                    119.309,
                    169.044,
                    117.764,
                    171.579,
                    80.678,
                    138.616,
                    82.705
                ]
            ],
            "iscrowd": 0
        },
        {
            "id": 191,
            "image_id": 18,
            "category_id": 19,
            "bbox": [
                475,
                88,
                62.546,
                71.082
            ],
            "area": 4445.882,
            "segmentation": [
                [
                    534.178,
                    155.622,
                    537.559,
                    87.631,
                    478.394,
                    88.502,
                    475.013,
                    151.76,
                    486.846,
                    153.305,
                    486.846,
                    158.713,
                    534.178,
                    155.622
                ]
            ],
            "iscrowd": 0
        },
        {
            "id": 192,
            "image_id": 18,
            "category_id": 17,
            "bbox": [
                467,
                166,
                75.224,
                58.72
            ],
            "area": 4417.173,
            "segmentation": [
                [
                    469.519,
                    167.343,
                    467.406,
                    224.387,
                    542.631,
                    222.842,
                    538.405,
                    165.667,
                    469.519,
                    167.343
                ]
            ],
            "iscrowd": 0
        },
        {
            "id": 193,
            "image_id": 18,
            "category_id": 18,
            "bbox": [
                355,
                231,
                180.032,
                101.215
            ],
            "area": 18221.838,
            "segmentation": [
                [
                    428.526,
                    331.782,
                    530.798,
                    330.237,
                    535.024,
                    293.924,
                    507.132,
                    290.833,
                    502.906,
                    230.568,
                    427.681,
                    231.111,
                    354.992,
                    231.341,
                    361.754,
                    280.789,
                    425.145,
                    276.153,
                    428.526,
                    331.782
                ]
            ],
            "iscrowd": 0
        },
        {
            "id": 194,
            "image_id": 18,
            "category_id": 22,
            "bbox": [
                512,
                232,
                25.357,
                48.676
            ],
            "area": 1234.249,
            "segmentation": [
                [
                    512.625,
                    232.27,
                    512.203,
                    280.789,
                    536.714,
                    280.789,
                    537.559,
                    232.113,
                    512.625,
                    232.27
                ]
            ],
            "iscrowd": 0
        },
        {
            "id": 195,
            "image_id": 18,
            "category_id": 14,
            "bbox": [
                344,
                332,
                192.71,
                213.82
            ],
            "area": 41205.305,
            "segmentation": [
                [
                    345.272,
                    331.981,
                    344.004,
                    545.801,
                    529.107,
                    545.801,
                    536.714,
                    342.599,
                    345.272,
                    331.981
                ]
            ],
            "iscrowd": 0
        },
        {
            "id": 196,
            "image_id": 18,
            "category_id": 14,
            "bbox": [
                139,
                337,
                191.865,
                209.183
            ],
            "area": 40134.737,
            "segmentation": [
                [
                    331.326,
                    336.618,
                    140.307,
                    337.964,
                    139.461,
                    545.801,
                    329.635,
                    542.71,
                    331.326,
                    336.618
                ]
            ],
            "iscrowd": 0
        },
        {
            "id": 197,
            "image_id": 18,
            "category_id": 12,
            "bbox": [
                0,
                0,
                639.493,
                639.536
            ],
            "area": 408978.859,
            "segmentation": [
                [
                    0.422,
                    1.546,
                    0,
                    639.536,
                    639.493,
                    639.289,
                    639.493,
                    0,
                    0.422,
                    1.546
                ]
            ],
            "iscrowd": 0
        }
    ],
    "categories": [
        {
            "id": 1,
            "name": "공간_다목적공간"
        },
        {
            "id": 2,
            "name": "공간_엘리베이터홀"
        },
        {
            "id": 3,
            "name": "공간_계단실"
        },
        {
            "id": 4,
            "name": "객체_변기"
        },
        {
            "id": 5,
            "name": "객체_세면대"
        },
        {
            "id": 6,
            "name": "객체_싱크대"
        },
        {
            "id": 7,
            "name": "객체_욕조"
        },
        {
            "id": 8,
            "name": "객체_가스레인지"
        },
        {
            "id": 9,
            "name": "구조_출입문"
        },
        {
            "id": 10,
            "name": "구조_창호"
        },
        {
            "id": 11,
            "name": "구조_벽체"
        },
        {
            "id": 12,
            "name": "background"
        },
        {
            "id": 13,
            "name": "공간_거실"
        },
        {
            "id": 14,
            "name": "공간_침실"
        },
        {
            "id": 15,
            "name": "공간_주방"
        },
        {
            "id": 16,
            "name": "공간_현관"
        },
        {
            "id": 17,
            "name": "공간_발코니"
        },
        {
            "id": 18,
            "name": "공간_화장실"
        },
        {
            "id": 19,
            "name": "공간_실외기실"
        },
        {
            "id": 20,
            "name": "공간_드레스룸"
        },
        {
            "id": 21,
            "name": "OCR"
        },
        {
            "id": 22,
            "name": "공간_기타"
        },
        {
            "id": 23,
            "name": "공간_엘리베이터"
        }
    ]
}